workstream_dbt_core/__init__.py
workstream_dbt_core/api.py
workstream_dbt_core/cli.py
workstream_dbt_core/exception.py
workstream_dbt_core/http.py
workstream_dbt_core/result.py
workstream_dbt_core-0.2.0.dist-info/METADATA
workstream_dbt_core-0.2.0.dist-info/WHEEL
workstream_dbt_core-0.2.0.dist-info/entry_points.txt
workstream_dbt_core-0.2.0.dist-info/RECORD
