Metadata-Version: 2.1
Name: workstream-dbt-core
Version: 0.2.0
Summary: A CLI and Python library for integrating Workstream and dbt-core.
License: Apache 2.0
Author: Ted Conbeer
Author-email: tconbeer@users.noreply.github.com
Requires-Python: >=3.8,<4.0
Classifier: License :: Other/Proprietary License
Classifier: Programming Language :: Python :: 3
Classifier: Programming Language :: Python :: 3.8
Classifier: Programming Language :: Python :: 3.9
Classifier: Programming Language :: Python :: 3.10
Classifier: Programming Language :: Python :: 3.11
Classifier: Programming Language :: Python :: 3.12
Requires-Dist: dbt-core (>=1.5,<2.0)
